dotyaml/__init__.py
dotyaml/interpolation.py
dotyaml/loader.py
dotyaml/transformer.py
dotyaml-0.1.3.dist-info/licenses/LICENSE
dotyaml-0.1.3.dist-info/METADATA
dotyaml-0.1.3.dist-info/WHEEL
dotyaml-0.1.3.dist-info/top_level.txt
dotyaml-0.1.3.dist-info/RECORD
