Metadata-Version: 2.4
Name: dotyaml
Version: 0.1.3
Summary: Bridge YAML configuration files and environment variables for flexible app deployment
Author: dotyaml contributors
License-Expression: MIT
Project-URL: Homepage, https://github.com/AnthusAI/dotyaml
Project-URL: Bug Reports, https://github.com/AnthusAI/dotyaml/issues
Project-URL: Source, https://github.com/AnthusAI/dotyaml
Keywords: yaml,environment,config,configuration,dotenv,12factor
Classifier: Development Status :: 3 - Alpha
Classifier: Intended Audience :: Developers
Classifier: Programming Language :: Python :: 3
Classifier: Programming Language :: Python :: 3.11
Classifier: Programming Language :: Python :: 3.12
Classifier: Topic :: Software Development :: Libraries :: Python Modules
Classifier: Topic :: System :: Systems Administration
Requires-Python: >=3.11
License-File: LICENSE
Requires-Dist: PyYAML>=6.0
Requires-Dist: python-dotenv>=1.0.0
Provides-Extra: dev
Requires-Dist: pytest>=8.0; extra == "dev"
Requires-Dist: pytest-bdd>=8.1.0; extra == "dev"
Requires-Dist: pytest-cov>=4.0; extra == "dev"
Requires-Dist: black>=23.0; extra == "dev"
Requires-Dist: flake8>=6.0; extra == "dev"
Requires-Dist: mypy>=1.0; extra == "dev"
Requires-Dist: types-PyYAML>=6.0; extra == "dev"
Requires-Dist: pre-commit>=3.0; extra == "dev"
Dynamic: license-file
